synthdog/__init__.py
synthdog/template.py
synthdog/config/config_en.yaml
synthdog/config/config_ja.yaml
synthdog/config/config_ko.yaml
synthdog/config/config_zh.yaml
synthdog/elements/__init__.py
synthdog/elements/background.py
synthdog/elements/content.py
synthdog/elements/document.py
synthdog/elements/paper.py
synthdog/elements/textbox.py
synthdog/elements/utils.py
synthdog/layouts/__init__.py
synthdog/layouts/grid.py
synthdog/layouts/grid_stack.py
synthdog/resources/background/82092117.png
synthdog/resources/background/82200067_0069.png
synthdog/resources/background/82250337_0338.png
synthdog/resources/background/82251504.png
synthdog/resources/background/82252956_2958.png
synthdog/resources/background/82253058_3059.png
synthdog/resources/background/82253245_3247.png
synthdog/resources/background/82253362_3364.png
synthdog/resources/background/82254765.png
synthdog/resources/background/82491256.png
synthdog/resources/background/82504862.png
synthdog/resources/background/82562350.png
synthdog/resources/background/82573104.png
synthdog/resources/background/82837252.png
synthdog/resources/background/83443897.png
synthdog/resources/background/83553333_3334.png
synthdog/resources/background/83573282.png
synthdog/resources/background/83594639.png
synthdog/resources/background/83624198.png
synthdog/resources/background/83635935.png
synthdog/resources/background/83641919_1921.png
synthdog/resources/background/83772145.png
synthdog/resources/background/83823750.png
synthdog/resources/background/83996357.png
synthdog/resources/background/85201976.png
synthdog/resources/background/85240939.png
synthdog/resources/background/85540866.png
synthdog/resources/background/85629964.png
synthdog/resources/background/86075409_5410.png
synthdog/resources/background/86079776_9777.png
synthdog/resources/background/86220490.png
synthdog/resources/background/86230203_0206.png
synthdog/resources/background/86236474_6476.png
synthdog/resources/background/86244113.png
synthdog-0.8.2.dist-info/METADATA
synthdog-0.8.2.dist-info/NOTICE
synthdog-0.8.2.dist-info/WHEEL
synthdog-0.8.2.dist-info/top_level.txt
synthdog-0.8.2.dist-info/RECORD
