Metadata-Version: 2.1
Name: synthdog
Version: 0.8.2
Summary: Customized synthdog package from donut-python project
Home-page: https://github.com/bilykigor/synthdog.git
Author: ML Team
Author-email: bilyk.box@gmail.com
License: MIT
Classifier: Intended Audience :: Developers
Classifier: Intended Audience :: Information Technology
Classifier: Intended Audience :: Science/Research
Classifier: Natural Language :: English
Classifier: License :: OSI Approved :: MIT License
Classifier: Programming Language :: Python
Classifier: Programming Language :: Python :: 3.7
Classifier: Programming Language :: Python :: 3.8
Classifier: Programming Language :: Python :: 3.9
Classifier: Programming Language :: Python :: 3.10
Classifier: Topic :: Scientific/Engineering :: Artificial Intelligence
Classifier: Topic :: Software Development :: Libraries
Classifier: Topic :: Software Development :: Libraries :: Python Modules
Requires-Python: >=3.7
License-File: NOTICE
Requires-Dist: synthtiger ==1.2.1
Requires-Dist: Pillow ==9.4.0
Requires-Dist: random-address ==1.1.1
Requires-Dist: unidecode ==1.3.4
